{"cameraMode":{"drawMode":0,"name":"Shaded","section":"Shading Mode"},"sceneLighting":false,"audioPlay":false,"sceneViewState":{"m_AlwaysRefresh":false,"showFog":true,"showSkybox":false,"showFlares":true,"showImageEffects":true,"showParticleSystems":true,"showVisualEffectGraphs":true,"m_FxEnabled":true},"in2DMode":false,"pivot":{"x":-4.304736614227295,"y":10.604942321777344,"z":2.060767889022827},"rotation":{"x":-0.18658758699893952,"y":0.0354553684592247,"z":-0.006738733500242233,"w":-0.9817871451377869},"size":9.524574279785157,"orthographic":false}